robin_api/__init__.py
robin_api/_client.py
robin_api/_compat.py
robin_api/_constants.py
robin_api/_exceptions.py
robin_api/_models.py
robin_api/_resource.py
robin_api/_streaming.py
robin_api/_types.py
robin_api/_utils/__init__.py
robin_api/_utils/_utils.py
robin_api/resources/FineTuning.py
robin_api/resources/__init__.py
robin_api/resources/completions.py
robin_api/resources/files.py
robin_api/types/__init__.py
robin_api/types/chat_completion.py
robin_api/types/chat_completion_chunk.py
robin_api/types/chat_completion_message.py
robin_api/types/chat_completion_message_tool_call.py
robin_api/types/chat_completion_tool_param.py
robin_api/types/chat_completion_tool_param_legacy.py
robin_api/types/completion.py
robin_api/types/completion_choice.py
robin_api/types/completion_usage.py
robin_api/types/docs_response.py
robin_api/types/file_model.py
robin_api/types/fine_tunning_model.py
robin_api/types/models_robin.py
robin_api-2.24.dist-info/licenses/LICENSE
robin_api-2.24.dist-info/METADATA
robin_api-2.24.dist-info/WHEEL
robin_api-2.24.dist-info/top_level.txt
robin_api-2.24.dist-info/RECORD
