Metadata-Version: 2.4
Name: robin_api
Version: 2.24
Summary: RobinApi Framework - LLM API integration and vector database management
Home-page: https://github.com/williamgomez71/RobinApi
Author: William Gomez
Author-email: william.gomez712@gmail.com
License: MIT
Classifier: Programming Language :: Python :: 3
Classifier: License :: OSI Approved :: MIT License
Classifier: Operating System :: OS Independent
Requires-Python: >=3.3
Requires-Dist: httpx
Requires-Dist: pydantic
Requires-Dist: distro
Requires-Dist: validators
Requires-Dist: pandas
Dynamic: author
Dynamic: author-email
Dynamic: classifier
Dynamic: description
Dynamic: description-content-type
Dynamic: home-page
Dynamic: license
Dynamic: requires-dist
Dynamic: requires-python
Dynamic: summary
